{
"meta":{"test_sets":[],"test_metrics":[],"learn_metrics":[{"best_value":"Min","name":"Logloss"}],"launch_mode":"Train","parameters":"","iteration_count":500,"learn_sets":["learn"],"name":"experiment"},
"iterations":[
{"learn":[0.684248967],"iteration":0,"passed_time":0.01513084096,"remaining_time":7.550289637},
{"learn":[0.6748686833],"iteration":1,"passed_time":0.02683633992,"remaining_time":6.682248639},
{"learn":[0.6665192789],"iteration":2,"passed_time":0.04009591948,"remaining_time":6.642557327},
{"learn":[0.6586772862],"iteration":3,"passed_time":0.05187935045,"remaining_time":6.433039456},
{"learn":[0.6510092323],"iteration":4,"passed_time":0.06381662457,"remaining_time":6.317845833},
{"learn":[0.6429074416],"iteration":5,"passed_time":0.07469765365,"remaining_time":6.150106817},
{"learn":[0.6340485758],"iteration":6,"passed_time":0.08351961793,"remaining_time":5.882167377},
{"learn":[0.6265968778],"iteration":7,"passed_time":0.0948883731,"remaining_time":5.835634945},
{"learn":[0.6194263287],"iteration":8,"passed_time":0.1065576549,"remaining_time":5.813312062},
{"learn":[0.6127381965],"iteration":9,"passed_time":0.108220038,"remaining_time":5.302781861},
{"learn":[0.6058760686],"iteration":10,"passed_time":0.1203239836,"remaining_time":5.348947997},
{"learn":[0.5993211661],"iteration":11,"passed_time":0.1316413514,"remaining_time":5.353414956},
{"learn":[0.5925692658],"iteration":12,"passed_time":0.1463525808,"remaining_time":5.482592833},
{"learn":[0.5864203154],"iteration":13,"passed_time":0.1527303759,"remaining_time":5.301925907},
{"learn":[0.5787280638],"iteration":14,"passed_time":0.1643035986,"remaining_time":5.312483022},
{"learn":[0.5721524367],"iteration":15,"passed_time":0.1798619647,"remaining_time":5.440824434},
{"learn":[0.566621695],"iteration":16,"passed_time":0.1860007021,"remaining_time":5.284608184},
{"learn":[0.5612342607],"iteration":17,"passed_time":0.1941935355,"remaining_time":5.200071341},
{"learn":[0.5552583381],"iteration":18,"passed_time":0.203912403,"remaining_time":5.162203465},
{"learn":[0.5493563752],"iteration":19,"passed_time":0.2129402818,"remaining_time":5.110566762},
{"learn":[0.5428441745],"iteration":20,"passed_time":0.2221091523,"remaining_time":5.066203998},
{"learn":[0.536584484],"iteration":21,"passed_time":0.2376818207,"remaining_time":5.164177741},
{"learn":[0.5311513303],"iteration":22,"passed_time":0.2617426464,"remaining_time":5.428314884},
{"learn":[0.5256171725],"iteration":23,"passed_time":0.2748385733,"remaining_time":5.450965038},
{"learn":[0.5205213632],"iteration":24,"passed_time":0.2911841802,"remaining_time":5.532499424},
{"learn":[0.5147382822],"iteration":25,"passed_time":0.3066855193,"remaining_time":5.591112928},
{"learn":[0.5094088654],"iteration":26,"passed_time":0.3248979798,"remaining_time":5.691731275},
{"learn":[0.5041823885],"iteration":27,"passed_time":0.3438036759,"remaining_time":5.795547679},
{"learn":[0.4986367866],"iteration":28,"passed_time":0.3625390517,"remaining_time":5.888134253},
{"learn":[0.4941636271],"iteration":29,"passed_time":0.3779206228,"remaining_time":5.920756424},
{"learn":[0.488517932],"iteration":30,"passed_time":0.395396501,"remaining_time":5.981966418},
{"learn":[0.4844139441],"iteration":31,"passed_time":0.4021832692,"remaining_time":5.881930312},
{"learn":[0.4794661109],"iteration":32,"passed_time":0.4089848757,"remaining_time":5.787755666},
{"learn":[0.4748391393],"iteration":33,"passed_time":0.4157383307,"remaining_time":5.69806065},
{"learn":[0.4706426307],"iteration":34,"passed_time":0.4231561137,"remaining_time":5.621931225},
{"learn":[0.4662326699],"iteration":35,"passed_time":0.4298925995,"remaining_time":5.54083795},
{"learn":[0.4614414101],"iteration":36,"passed_time":0.4375313983,"remaining_time":5.475055065},
{"learn":[0.4567500727],"iteration":37,"passed_time":0.4478060023,"remaining_time":5.444378239},
{"learn":[0.4530706833],"iteration":38,"passed_time":0.4549207348,"remaining_time":5.377396378},
{"learn":[0.4478981815],"iteration":39,"passed_time":0.4605295143,"remaining_time":5.296089414},
{"learn":[0.4442639137],"iteration":40,"passed_time":0.4668746991,"remaining_time":5.226719192},
{"learn":[0.4397959638],"iteration":41,"passed_time":0.4727383545,"remaining_time":5.155099199},
{"learn":[0.4350992744],"iteration":42,"passed_time":0.4783696598,"remaining_time":5.084068245},
{"learn":[0.4309788035],"iteration":43,"passed_time":0.484022855,"remaining_time":5.016236861},
{"learn":[0.4268065495],"iteration":44,"passed_time":0.4897916043,"remaining_time":4.952337332},
{"learn":[0.4226165885],"iteration":45,"passed_time":0.495767418,"remaining_time":4.893008864},
{"learn":[0.4185359442],"iteration":46,"passed_time":0.5014685687,"remaining_time":4.833303439},
{"learn":[0.4151568057],"iteration":47,"passed_time":0.5071703974,"remaining_time":4.775854575},
{"learn":[0.4105714826],"iteration":48,"passed_time":0.5130637123,"remaining_time":4.722280291},
{"learn":[0.406865248],"iteration":49,"passed_time":0.5188200052,"remaining_time":4.669380047},
{"learn":[0.4033116867],"iteration":50,"passed_time":0.5242115497,"remaining_time":4.615117369},
{"learn":[0.3999129907],"iteration":51,"passed_time":0.5297146356,"remaining_time":4.563695322},
{"learn":[0.396604965],"iteration":52,"passed_time":0.5352955714,"remaining_time":4.51466265},
{"learn":[0.3938252748],"iteration":53,"passed_time":0.5409306075,"remaining_time":4.467686129},
{"learn":[0.3907314699],"iteration":54,"passed_time":0.546577327,"remaining_time":4.422307464},
{"learn":[0.3884035936],"iteration":55,"passed_time":0.5526543556,"remaining_time":4.381759533},
{"learn":[0.3854934351],"iteration":56,"passed_time":0.5584477646,"remaining_time":4.340216837},
{"learn":[0.3816987223],"iteration":57,"passed_time":0.564545578,"remaining_time":4.302226646},
{"learn":[0.3784795163],"iteration":58,"passed_time":0.5722922483,"remaining_time":4.277642059},
{"learn":[0.3752772203],"iteration":59,"passed_time":0.5780304451,"remaining_time":4.238889931},
{"learn":[0.3724000276],"iteration":60,"passed_time":0.5837207974,"remaining_time":4.200875902},
{"learn":[0.3699222679],"iteration":61,"passed_time":0.5897249186,"remaining_time":4.166121199},
{"learn":[0.3676659598],"iteration":62,"passed_time":0.5915195559,"remaining_time":4.103080094},
{"learn":[0.3644826804],"iteration":63,"passed_time":0.5971912132,"remaining_time":4.06836514},
{"learn":[0.3615048537],"iteration":64,"passed_time":0.6034164171,"remaining_time":4.03824833},
{"learn":[0.358749532],"iteration":65,"passed_time":0.6094699928,"remaining_time":4.007726922},
{"learn":[0.3559524195],"iteration":66,"passed_time":0.6150133046,"remaining_time":3.974638222},
{"learn":[0.3532683529],"iteration":67,"passed_time":0.620759315,"remaining_time":3.943647413},
{"learn":[0.3504157849],"iteration":68,"passed_time":0.6266262013,"remaining_time":3.914143373},
{"learn":[0.3474747387],"iteration":69,"passed_time":0.6323364376,"remaining_time":3.884352402},
{"learn":[0.3448664822],"iteration":70,"passed_time":0.6385652323,"remaining_time":3.858373023},
{"learn":[0.3421941729],"iteration":71,"passed_time":0.6443185284,"remaining_time":3.830115697},
{"learn":[0.3396542108],"iteration":72,"passed_time":0.6497147897,"remaining_time":3.80038651},
{"learn":[0.3372569013],"iteration":73,"passed_time":0.6553588343,"remaining_time":3.772741398},
{"learn":[0.3345922214],"iteration":74,"passed_time":0.6611131623,"remaining_time":3.74630792},
{"learn":[0.3317887605],"iteration":75,"passed_time":0.6667455096,"remaining_time":3.719738106},
{"learn":[0.3289107707],"iteration":76,"passed_time":0.6730568891,"remaining_time":3.697442391},
{"learn":[0.3265048354],"iteration":77,"passed_time":0.6787839175,"remaining_time":3.672395041},
{"learn":[0.3240263925],"iteration":78,"passed_time":0.6846816232,"remaining_time":3.648746372},
{"learn":[0.3215139588],"iteration":79,"passed_time":0.6902872588,"remaining_time":3.624008109},
{"learn":[0.3192342787],"iteration":80,"passed_time":0.6960986749,"remaining_time":3.600806726},
{"learn":[0.3171129369],"iteration":81,"passed_time":0.7019371146,"remaining_time":3.578167243},
{"learn":[0.3147757231],"iteration":82,"passed_time":0.7078768982,"remaining_time":3.556441765},
{"learn":[0.3128910349],"iteration":83,"passed_time":0.7167436631,"remaining_time":3.549587665},
{"learn":[0.3111388932],"iteration":84,"passed_time":0.7187917985,"remaining_time":3.509395252},
{"learn":[0.3092391455],"iteration":85,"passed_time":0.7246459914,"remaining_time":3.488412098},
{"learn":[0.3074597031],"iteration":86,"passed_time":0.7307425249,"remaining_time":3.468927159},
{"learn":[0.3053488945],"iteration":87,"passed_time":0.7366749138,"remaining_time":3.448978006},
{"learn":[0.3030459276],"iteration":88,"passed_time":0.7429914171,"remaining_time":3.431117668},
{"learn":[0.301459896],"iteration":89,"passed_time":0.7487205134,"remaining_time":3.410837895},
{"learn":[0.2997706968],"iteration":90,"passed_time":0.754443605,"remaining_time":3.390850928},
{"learn":[0.2978539538],"iteration":91,"passed_time":0.7607786084,"remaining_time":3.373887741},
{"learn":[0.296251781],"iteration":92,"passed_time":0.7666988529,"remaining_time":3.355337991},
{"learn":[0.2939496112],"iteration":93,"passed_time":0.7724918619,"remaining_time":3.336507404},
{"learn":[0.2921530595],"iteration":94,"passed_time":0.7782363084,"remaining_time":3.317744262},
{"learn":[0.290195579],"iteration":95,"passed_time":0.7814006388,"remaining_time":3.288394355},
{"learn":[0.2885202436],"iteration":96,"passed_time":0.7868801558,"remaining_time":3.269203122},
{"learn":[0.2866131227],"iteration":97,"passed_time":0.7922094656,"remaining_time":3.249675563},
{"learn":[0.2849131342],"iteration":98,"passed_time":0.7981132399,"remaining_time":3.232761709},
{"learn":[0.2832923718],"iteration":99,"passed_time":0.8041503115,"remaining_time":3.216601246},
{"learn":[0.2814064026],"iteration":100,"passed_time":0.8095562473,"remaining_time":3.198147947},
{"learn":[0.2793015722],"iteration":101,"passed_time":0.8166795194,"remaining_time":3.186651458},
{"learn":[0.2773775414],"iteration":102,"passed_time":0.8223412051,"remaining_time":3.169606392},
{"learn":[0.2758036941],"iteration":103,"passed_time":0.8278780742,"remaining_time":3.152304975},
{"learn":[0.274241604],"iteration":104,"passed_time":0.8334987341,"remaining_time":3.135542857},
{"learn":[0.2727067862],"iteration":105,"passed_time":0.8391082885,"remaining_time":3.118949676},
{"learn":[0.2714034977],"iteration":106,"passed_time":0.8450299659,"remaining_time":3.103708193},
{"learn":[0.269926669],"iteration":107,"passed_time":0.8507151255,"remaining_time":3.087780826},
{"learn":[0.2685128397],"iteration":108,"passed_time":0.8563978691,"remaining_time":3.072032723},
{"learn":[0.2671204752],"iteration":109,"passed_time":0.8625297838,"remaining_time":3.058060143},
{"learn":[0.265437966],"iteration":110,"passed_time":0.8686118121,"remaining_time":3.044054008},
{"learn":[0.2643334688],"iteration":111,"passed_time":0.874798842,"remaining_time":3.030553131},
{"learn":[0.2628069636],"iteration":112,"passed_time":0.8805982587,"remaining_time":3.015854213},
{"learn":[0.2613683957],"iteration":113,"passed_time":0.8862834123,"remaining_time":3.000924536},
{"learn":[0.2601519343],"iteration":114,"passed_time":0.8918613493,"remaining_time":2.985796691},
{"learn":[0.2584947899],"iteration":115,"passed_time":0.8972320929,"remaining_time":2.970147618},
{"learn":[0.2569760565],"iteration":116,"passed_time":0.9027249533,"remaining_time":2.955073992},
{"learn":[0.2554691941],"iteration":117,"passed_time":0.9082406235,"remaining_time":2.940236595},
{"learn":[0.2543227352],"iteration":118,"passed_time":0.9139185984,"remaining_time":2.926075512},
{"learn":[0.2527450448],"iteration":119,"passed_time":0.9194089059,"remaining_time":2.911461535},
{"learn":[0.2510313632],"iteration":120,"passed_time":0.9251177712,"remaining_time":2.897682936},
{"learn":[0.2498581445],"iteration":121,"passed_time":0.9306593501,"remaining_time":2.883518314},
{"learn":[0.2484560155],"iteration":122,"passed_time":0.936024133,"remaining_time":2.868952017},
{"learn":[0.2470762338],"iteration":123,"passed_time":0.9417123714,"remaining_time":2.855514933},
{"learn":[0.2460235482],"iteration":124,"passed_time":0.9473493194,"remaining_time":2.842047958},
{"learn":[0.2446954357],"iteration":125,"passed_time":0.9527871595,"remaining_time":2.828114267},
{"learn":[0.2434539795],"iteration":126,"passed_time":0.9581530654,"remaining_time":2.814103098},
{"learn":[0.2424043684],"iteration":127,"passed_time":0.9637644307,"remaining_time":2.800940377},
{"learn":[0.240961331],"iteration":128,"passed_time":0.9691450748,"remaining_time":2.787231184},
{"learn":[0.2392691997],"iteration":129,"passed_time":0.9748578459,"remaining_time":2.774595408},
{"learn":[0.2379461118],"iteration":130,"passed_time":0.9809499117,"remaining_time":2.763133721},
{"learn":[0.236759442],"iteration":131,"passed_time":0.9867046587,"remaining_time":2.750812988},
{"learn":[0.2358381072],"iteration":132,"passed_time":0.992199333,"remaining_time":2.737873347},
{"learn":[0.2347683693],"iteration":133,"passed_time":0.9976824338,"remaining_time":2.725013215},
{"learn":[0.2335176468],"iteration":134,"passed_time":1.003390057,"remaining_time":2.712869414},
{"learn":[0.2323187643],"iteration":135,"passed_time":1.009387057,"remaining_time":2.70159477},
{"learn":[0.2308474726],"iteration":136,"passed_time":1.01541415,"remaining_time":2.690476908},
{"learn":[0.2296752076],"iteration":137,"passed_time":1.021494542,"remaining_time":2.67957264},
{"learn":[0.2284565541],"iteration":138,"passed_time":1.027600139,"remaining_time":2.668803239},
{"learn":[0.2276491194],"iteration":139,"passed_time":1.033268032,"remaining_time":2.656974939},
{"learn":[0.2265083398],"iteration":140,"passed_time":1.038824431,"remaining_time":2.644950147},
{"learn":[0.2254151871],"iteration":141,"passed_time":1.044396826,"remaining_time":2.633056787},
{"learn":[0.2244731134],"iteration":142,"passed_time":1.049730017,"remaining_time":2.620654657},
{"learn":[0.2235077246],"iteration":143,"passed_time":1.055472024,"remaining_time":2.609361393},
{"learn":[0.2225040037],"iteration":144,"passed_time":1.061069873,"remaining_time":2.597791759},
{"learn":[0.2212768384],"iteration":145,"passed_time":1.066411638,"remaining_time":2.585683014},
{"learn":[0.2200422287],"iteration":146,"passed_time":1.071856326,"remaining_time":2.573913491},
{"learn":[0.2187927303],"iteration":147,"passed_time":1.077328026,"remaining_time":2.562293683},
{"learn":[0.2176616726],"iteration":148,"passed_time":1.083049794,"remaining_time":2.551345489},
{"learn":[0.2168162332],"iteration":149,"passed_time":1.088651979,"remaining_time":2.540187951},
{"learn":[0.2157306671],"iteration":150,"passed_time":1.094456972,"remaining_time":2.529572736},
{"learn":[0.2149723964],"iteration":151,"passed_time":1.099735917,"remaining_time":2.517816441},
{"learn":[0.2142282457],"iteration":152,"passed_time":1.105142574,"remaining_time":2.506434464},
{"learn":[0.2129882414],"iteration":153,"passed_time":1.110491865,"remaining_time":2.495001204},
{"learn":[0.2118644145],"iteration":154,"passed_time":1.116383276,"remaining_time":2.484853099},
{"learn":[0.2108166111],"iteration":155,"passed_time":1.122067201,"remaining_time":2.474302033},
{"learn":[0.2099332952],"iteration":156,"passed_time":1.127503958,"remaining_time":2.463272979},
{"learn":[0.2090649107],"iteration":157,"passed_time":1.132887727,"remaining_time":2.452200017},
{"learn":[0.2076932565],"iteration":158,"passed_time":1.138452161,"remaining_time":2.441586081},
{"learn":[0.2068186233],"iteration":159,"passed_time":1.144524175,"remaining_time":2.432113871},
{"learn":[0.2057412845],"iteration":160,"passed_time":1.149998955,"remaining_time":2.421426371},
{"learn":[0.2050405474],"iteration":161,"passed_time":1.155761601,"remaining_time":2.411403835},
{"learn":[0.2039657707],"iteration":162,"passed_time":1.16152417,"remaining_time":2.401433407},
{"learn":[0.2031858074],"iteration":163,"passed_time":1.167418662,"remaining_time":2.391784576},
{"learn":[0.2025248542],"iteration":164,"passed_time":1.173644712,"remaining_time":2.382854415},
{"learn":[0.2014711864],"iteration":165,"passed_time":1.179997816,"remaining_time":2.374212474},
{"learn":[0.2004946524],"iteration":166,"passed_time":1.185315572,"remaining_time":2.363533445},
{"learn":[0.1997614334],"iteration":167,"passed_time":1.190744621,"remaining_time":2.35313818},
{"learn":[0.1990840542],"iteration":168,"passed_time":1.196220481,"remaining_time":2.342893369},
{"learn":[0.1979698352],"iteration":169,"passed_time":1.204400929,"remaining_time":2.337954745},
{"learn":[0.1970996003],"iteration":170,"passed_time":1.212236864,"remaining_time":2.33231537},
{"learn":[0.1962514991],"iteration":171,"passed_time":1.219180581,"remaining_time":2.324949016},
{"learn":[0.1955738637],"iteration":172,"passed_time":1.231362889,"remaining_time":2.327489391},
{"learn":[0.1947591554],"iteration":173,"passed_time":1.240940084,"remaining_time":2.324979697},
{"learn":[0.1939994186],"iteration":174,"passed_time":1.247086873,"remaining_time":2.316018478},
{"learn":[0.1931166862],"iteration":175,"passed_time":1.252730811,"remaining_time":2.306163539},
{"learn":[0.1923241829],"iteration":176,"passed_time":1.258432187,"remaining_time":2.296460997},
{"learn":[0.1915766446],"iteration":177,"passed_time":1.264256339,"remaining_time":2.287025513},
{"learn":[0.190843269],"iteration":178,"passed_time":1.269922461,"remaining_time":2.277346983},
{"learn":[0.1898956584],"iteration":179,"passed_time":1.275512881,"remaining_time":2.267578456},
{"learn":[0.1890294943],"iteration":180,"passed_time":1.281031053,"remaining_time":2.257728763},
{"learn":[0.1881326989],"iteration":181,"passed_time":1.291937103,"remaining_time":2.257340653},
{"learn":[0.187318446],"iteration":182,"passed_time":1.301857081,"remaining_time":2.25512948},
{"learn":[0.1866314447],"iteration":183,"passed_time":1.307341111,"remaining_time":2.245216256},
{"learn":[0.1859083887],"iteration":184,"passed_time":1.312709551,"remaining_time":2.2351541},
{"learn":[0.1850953031],"iteration":185,"passed_time":1.318375759,"remaining_time":2.225645099},
{"learn":[0.1842266624],"iteration":186,"passed_time":1.324378298,"remaining_time":2.216740145},
{"learn":[0.1835631755],"iteration":187,"passed_time":1.329807097,"remaining_time":2.206913906},
{"learn":[0.182677454],"iteration":188,"passed_time":1.33590366,"remaining_time":2.198233006},
{"learn":[0.1818414944],"iteration":189,"passed_time":1.341586318,"remaining_time":2.188903992},
{"learn":[0.1809051286],"iteration":190,"passed_time":1.347980889,"remaining_time":2.180764894},
{"learn":[0.1799765345],"iteration":191,"passed_time":1.353663008,"remaining_time":2.171501075},
{"learn":[0.1793298721],"iteration":192,"passed_time":1.359280784,"remaining_time":2.162172024},
{"learn":[0.1783393461],"iteration":193,"passed_time":1.364686658,"remaining_time":2.152546997},
{"learn":[0.177610924],"iteration":194,"passed_time":1.371151949,"remaining_time":2.144622279},
{"learn":[0.1768125847],"iteration":195,"passed_time":1.376512976,"remaining_time":2.134999718},
{"learn":[0.1761431054],"iteration":196,"passed_time":1.382079946,"remaining_time":2.125737175},
{"learn":[0.1753039004],"iteration":197,"passed_time":1.387628264,"remaining_time":2.116483514},
{"learn":[0.1746125577],"iteration":198,"passed_time":1.393340007,"remaining_time":2.107514283},
{"learn":[0.1739056288],"iteration":199,"passed_time":1.398957964,"remaining_time":2.098436947},
{"learn":[0.1733129701],"iteration":200,"passed_time":1.405698498,"remaining_time":2.091063935},
{"learn":[0.1725420738],"iteration":201,"passed_time":1.411583242,"remaining_time":2.082434684},
{"learn":[0.1719023861],"iteration":202,"passed_time":1.417333863,"remaining_time":2.073636242},
{"learn":[0.1712661857],"iteration":203,"passed_time":1.422936763,"remaining_time":2.064653343},
{"learn":[0.1703683939],"iteration":204,"passed_time":1.428827449,"remaining_time":2.056117549},
{"learn":[0.1697385418],"iteration":205,"passed_time":1.434524772,"remaining_time":2.047331471},
{"learn":[0.1691936379],"iteration":206,"passed_time":1.439876675,"remaining_time":2.038086308},
{"learn":[0.1686718215],"iteration":207,"passed_time":1.445262083,"remaining_time":2.028925616},
{"learn":[0.1680173874],"iteration":208,"passed_time":1.450997477,"remaining_time":2.020288353},
{"learn":[0.167552094],"iteration":209,"passed_time":1.456429838,"remaining_time":2.011260253},
{"learn":[0.1669158651],"iteration":210,"passed_time":1.461799954,"remaining_time":2.002180979},
{"learn":[0.1663530264],"iteration":211,"passed_time":1.467331756,"remaining_time":1.993356348},
{"learn":[0.1656378988],"iteration":212,"passed_time":1.472626532,"remaining_time":1.984243261},
{"learn":[0.1649757499],"iteration":213,"passed_time":1.478382551,"remaining_time":1.975782287},
{"learn":[0.1645739256],"iteration":214,"passed_time":1.483733582,"remaining_time":1.966809632},
{"learn":[0.1638438808],"iteration":215,"passed_time":1.48933858,"remaining_time":1.958204429},
{"learn":[0.1633761107],"iteration":216,"passed_time":1.494973098,"remaining_time":1.949665377},
{"learn":[0.1626892659],"iteration":217,"passed_time":1.500316273,"remaining_time":1.940776096},
{"learn":[0.1620432299],"iteration":218,"passed_time":1.50565368,"remaining_time":1.9319118},
{"learn":[0.1615290286],"iteration":219,"passed_time":1.509533394,"remaining_time":1.92122432},
{"learn":[0.1610941673],"iteration":220,"passed_time":1.515565583,"remaining_time":1.913315826},
{"learn":[0.1607014243],"iteration":221,"passed_time":1.521298693,"remaining_time":1.905049715},
{"learn":[0.1600677718],"iteration":222,"passed_time":1.52691852,"remaining_time":1.896665605},
{"learn":[0.1595431228],"iteration":223,"passed_time":1.532403703,"remaining_time":1.888140276},
{"learn":[0.1589389773],"iteration":224,"passed_time":1.538035481,"remaining_time":1.879821143},
{"learn":[0.1584295586],"iteration":225,"passed_time":1.543384724,"remaining_time":1.871183249},
{"learn":[0.1578609552],"iteration":226,"passed_time":1.548764821,"remaining_time":1.862611436},
{"learn":[0.1572894054],"iteration":227,"passed_time":1.554242162,"remaining_time":1.854183632},
{"learn":[0.1565618088],"iteration":228,"passed_time":1.559963048,"remaining_time":1.846069807},
{"learn":[0.1561624043],"iteration":229,"passed_time":1.565505035,"remaining_time":1.837766781},
{"learn":[0.1554586781],"iteration":230,"passed_time":1.570995843,"remaining_time":1.829428059},
{"learn":[0.1549607177],"iteration":231,"passed_time":1.576371106,"remaining_time":1.820980416},
{"learn":[0.1542348435],"iteration":232,"passed_time":1.581981437,"remaining_time":1.812828513},
{"learn":[0.1536632367],"iteration":233,"passed_time":1.587246663,"remaining_time":1.804306035},
{"learn":[0.1531554265],"iteration":234,"passed_time":1.593143103,"remaining_time":1.796523074},
{"learn":[0.1525896129],"iteration":235,"passed_time":1.599032171,"remaining_time":1.788747852},
{"learn":[0.1520648074],"iteration":236,"passed_time":1.604343166,"remaining_time":1.780347058},
{"learn":[0.1516479378],"iteration":237,"passed_time":1.609761119,"remaining_time":1.772089972},
{"learn":[0.1512429536],"iteration":238,"passed_time":1.615630118,"remaining_time":1.764349208},
{"learn":[0.1507546297],"iteration":239,"passed_time":1.621665761,"remaining_time":1.756804575},
{"learn":[0.1501587683],"iteration":240,"passed_time":1.627325642,"remaining_time":1.748868636},
{"learn":[0.1498249965],"iteration":241,"passed_time":1.632607512,"remaining_time":1.740548505},
{"learn":[0.1492905973],"iteration":242,"passed_time":1.638440895,"remaining_time":1.732836667},
{"learn":[0.1489176252],"iteration":243,"passed_time":1.644531416,"remaining_time":1.72541001},
{"learn":[0.1482741797],"iteration":244,"passed_time":1.650098405,"remaining_time":1.71744936},
{"learn":[0.1476567681],"iteration":245,"passed_time":1.655601153,"remaining_time":1.709441841},
{"learn":[0.1472255508],"iteration":246,"passed_time":1.661358613,"remaining_time":1.701715503},
{"learn":[0.1466616161],"iteration":247,"passed_time":1.666928646,"remaining_time":1.693814592},
{"learn":[0.1461141928],"iteration":248,"passed_time":1.672581863,"remaining_time":1.686016255},
{"learn":[0.1456106955],"iteration":249,"passed_time":1.67803699,"remaining_time":1.67803699},
{"learn":[0.1449029837],"iteration":250,"passed_time":1.683732129,"remaining_time":1.670315937},
{"learn":[0.1444920782],"iteration":251,"passed_time":1.689109232,"remaining_time":1.662297975},
{"learn":[0.1439092266],"iteration":252,"passed_time":1.694720076,"remaining_time":1.654529086},
{"learn":[0.143663321],"iteration":253,"passed_time":1.700202371,"remaining_time":1.64665269},
{"learn":[0.1432818228],"iteration":254,"passed_time":1.705698432,"remaining_time":1.638808297},
{"learn":[0.1427657853],"iteration":255,"passed_time":1.71133358,"remaining_time":1.631114818},
{"learn":[0.1421675896],"iteration":256,"passed_time":1.717251533,"remaining_time":1.623704757},
{"learn":[0.1418450768],"iteration":257,"passed_time":1.72299322,"remaining_time":1.616140928},
{"learn":[0.141411639],"iteration":258,"passed_time":1.72862264,"remaining_time":1.608486703},
{"learn":[0.1409203544],"iteration":259,"passed_time":1.734065983,"remaining_time":1.600676292},
{"learn":[0.1404715581],"iteration":260,"passed_time":1.739547413,"remaining_time":1.592918895},
{"learn":[0.1399593923],"iteration":261,"passed_time":1.745186551,"remaining_time":1.585322134},
{"learn":[0.1393430624],"iteration":262,"passed_time":1.751095647,"remaining_time":1.57798353},
{"learn":[0.1389940888],"iteration":263,"passed_time":1.756486044,"remaining_time":1.57019207},
{"learn":[0.1386386245],"iteration":264,"passed_time":1.762023552,"remaining_time":1.562549188},
{"learn":[0.1382549343],"iteration":265,"passed_time":1.768037113,"remaining_time":1.555340919},
{"learn":[0.1378873427],"iteration":266,"passed_time":1.773509719,"remaining_time":1.54766953},
{"learn":[0.1374868421],"iteration":267,"passed_time":1.774647578,"remaining_time":1.536262083},
{"learn":[0.1371619096],"iteration":268,"passed_time":1.780213205,"remaining_time":1.528733273},
{"learn":[0.1367897916],"iteration":269,"passed_time":1.785608754,"remaining_time":1.521074124},
{"learn":[0.1363277008],"iteration":270,"passed_time":1.791125925,"remaining_time":1.513534454},
{"learn":[0.1358641439],"iteration":271,"passed_time":1.796317117,"remaining_time":1.505736407},
{"learn":[0.1354006867],"iteration":272,"passed_time":1.801756152,"remaining_time":1.49816354},
{"learn":[0.1349585804],"iteration":273,"passed_time":1.807148268,"remaining_time":1.490567549},
{"learn":[0.1345755164],"iteration":274,"passed_time":1.81288995,"remaining_time":1.483273596},
{"learn":[0.1339914407],"iteration":275,"passed_time":1.818254046,"remaining_time":1.475684443},
{"learn":[0.1335819871],"iteration":276,"passed_time":1.823797578,"remaining_time":1.468255812},
{"learn":[0.1330724118],"iteration":277,"passed_time":1.829518494,"remaining_time":1.460982394},
{"learn":[0.1326555138],"iteration":278,"passed_time":1.835024961,"remaining_time":1.453550238},
{"learn":[0.1322092796],"iteration":279,"passed_time":1.840315209,"remaining_time":1.44596195},
{"learn":[0.1318928021],"iteration":280,"passed_time":1.845657408,"remaining_time":1.438430507},
{"learn":[0.1314191391],"iteration":281,"passed_time":1.851316671,"remaining_time":1.431159696},
{"learn":[0.1309604075],"iteration":282,"passed_time":1.857458246,"remaining_time":1.424270104},
{"learn":[0.1305058607],"iteration":283,"passed_time":1.863315085,"remaining_time":1.41716922},
{"learn":[0.1300000575],"iteration":284,"passed_time":1.869039652,"remaining_time":1.409977281},
{"learn":[0.1295098262],"iteration":285,"passed_time":1.874408503,"remaining_time":1.40252944},
{"learn":[0.129098878],"iteration":286,"passed_time":1.879853391,"remaining_time":1.395152517},
{"learn":[0.1285780722],"iteration":287,"passed_time":1.885110468,"remaining_time":1.387650761},
{"learn":[0.1281702127],"iteration":288,"passed_time":1.890687748,"remaining_time":1.380398321},
{"learn":[0.1277316506],"iteration":289,"passed_time":1.896112458,"remaining_time":1.373046952},
{"learn":[0.1272302457],"iteration":290,"passed_time":1.901825402,"remaining_time":1.365915838},
{"learn":[0.1270276824],"iteration":291,"passed_time":1.907411154,"remaining_time":1.358703836},
{"learn":[0.1267268764],"iteration":292,"passed_time":1.912697326,"remaining_time":1.351291285},
{"learn":[0.126272472],"iteration":293,"passed_time":1.918052176,"remaining_time":1.34394132},
{"learn":[0.1259084104],"iteration":294,"passed_time":1.923612746,"remaining_time":1.336747841},
{"learn":[0.1255061164],"iteration":295,"passed_time":1.929277571,"remaining_time":1.329637245},
{"learn":[0.1250553985],"iteration":296,"passed_time":1.934914201,"remaining_time":1.322517114},
{"learn":[0.1246501866],"iteration":297,"passed_time":1.940511284,"remaining_time":1.315380132},
{"learn":[0.12438646],"iteration":298,"passed_time":1.947372198,"remaining_time":1.309103049},
{"learn":[0.1240303125],"iteration":299,"passed_time":1.95440294,"remaining_time":1.302935294},
{"learn":[0.1235379746],"iteration":300,"passed_time":1.960175007,"remaining_time":1.295929655},
{"learn":[0.1231765178],"iteration":301,"passed_time":1.965834031,"remaining_time":1.288858074},
{"learn":[0.1227841164],"iteration":302,"passed_time":1.971486526,"remaining_time":1.281791569},
{"learn":[0.1224186456],"iteration":303,"passed_time":1.977080847,"remaining_time":1.274696862},
{"learn":[0.1221217397],"iteration":304,"passed_time":1.982653641,"remaining_time":1.26759823},
{"learn":[0.121770204],"iteration":305,"passed_time":1.988416527,"remaining_time":1.260630086},
{"learn":[0.121366387],"iteration":306,"passed_time":1.994098309,"remaining_time":1.253618807},
{"learn":[0.1208824329],"iteration":307,"passed_time":1.999651766,"remaining_time":1.246536166},
{"learn":[0.1205019453],"iteration":308,"passed_time":2.005782711,"remaining_time":1.239820381},
{"learn":[0.1201554768],"iteration":309,"passed_time":2.014039642,"remaining_time":1.234411393},
{"learn":[0.1197581505],"iteration":310,"passed_time":2.020568384,"remaining_time":1.227933841},
{"learn":[0.1193645961],"iteration":311,"passed_time":2.028075895,"remaining_time":1.222045732},
{"learn":[0.1189951754],"iteration":312,"passed_time":2.036748336,"remaining_time":1.216843255},
{"learn":[0.1186275197],"iteration":313,"passed_time":2.042902698,"remaining_time":1.210127076},
{"learn":[0.11815296],"iteration":314,"passed_time":2.048223155,"remaining_time":1.20292471},
{"learn":[0.1177507443],"iteration":315,"passed_time":2.053857033,"remaining_time":1.195916754},
{"learn":[0.1173617164],"iteration":316,"passed_time":2.059403985,"remaining_time":1.188867285},
{"learn":[0.1169859189],"iteration":317,"passed_time":2.065249705,"remaining_time":1.181998259},
{"learn":[0.1167428458],"iteration":318,"passed_time":2.070860829,"remaining_time":1.175002539},
{"learn":[0.1163344881],"iteration":319,"passed_time":2.076310593,"remaining_time":1.167924709},
{"learn":[0.1158177959],"iteration":320,"passed_time":2.081741323,"remaining_time":1.160846407},
{"learn":[0.1156833563],"iteration":321,"passed_time":2.082167158,"remaining_time":1.151011659},
{"learn":[0.1153442895],"iteration":322,"passed_time":2.08815964,"remaining_time":1.144285623},
{"learn":[0.1150700512],"iteration":323,"passed_time":2.094438949,"remaining_time":1.137719923},
{"learn":[0.1146931008],"iteration":324,"passed_time":2.100432404,"remaining_time":1.131002064},
{"learn":[0.1143101009],"iteration":325,"passed_time":2.106057724,"remaining_time":1.12409216},
{"learn":[0.1138389929],"iteration":326,"passed_time":2.111962446,"remaining_time":1.11733793},
{"learn":[0.1135721491],"iteration":327,"passed_time":2.120158248,"remaining_time":1.111790301},
{"learn":[0.1131807156],"iteration":328,"passed_time":2.126193696,"remaining_time":1.105103714},
{"learn":[0.1128976309],"iteration":329,"passed_time":2.131674908,"remaining_time":1.098135559},
{"learn":[0.1124943121],"iteration":330,"passed_time":2.137134042,"remaining_time":1.091165115},
{"learn":[0.1121067787],"iteration":331,"passed_time":2.142744848,"remaining_time":1.084280525},
{"learn":[0.1118427675],"iteration":332,"passed_time":2.14801587,"remaining_time":1.077233184},
{"learn":[0.1114854813],"iteration":333,"passed_time":2.154114134,"remaining_time":1.070607624},
{"learn":[0.1111091856],"iteration":334,"passed_time":2.160211668,"remaining_time":1.063984851},
{"learn":[0.1107812711],"iteration":335,"passed_time":2.166098821,"remaining_time":1.05726252},
{"learn":[0.1104500329],"iteration":336,"passed_time":2.17243496,"remaining_time":1.05076231},
{"learn":[0.1101526858],"iteration":337,"passed_time":2.178648252,"remaining_time":1.044204192},
{"learn":[0.1098798638],"iteration":338,"passed_time":2.193841857,"remaining_time":1.041913094},
{"learn":[0.1095724604],"iteration":339,"passed_time":2.206625602,"remaining_time":1.038412048},
{"learn":[0.1093193737],"iteration":340,"passed_time":2.218240433,"remaining_time":1.034311521},
{"learn":[0.1090030955],"iteration":341,"passed_time":2.228863681,"remaining_time":1.029708952},
{"learn":[0.1086095056],"iteration":342,"passed_time":2.239171234,"remaining_time":1.024926775},
{"learn":[0.1082620977],"iteration":343,"passed_time":2.249182263,"remaining_time":1.019978003},
{"learn":[0.1079162555],"iteration":344,"passed_time":2.255554133,"remaining_time":1.013364901},
{"learn":[0.1075689899],"iteration":345,"passed_time":2.261217697,"remaining_time":1.006437935},
{"learn":[0.1073048008],"iteration":346,"passed_time":2.266965705,"remaining_time":0.9995554839},
{"learn":[0.1069825443],"iteration":347,"passed_time":2.273147223,"remaining_time":0.9928689018},
{"learn":[0.1066775322],"iteration":348,"passed_time":2.279098877,"remaining_time":0.9860857608},
{"learn":[0.1063261957],"iteration":349,"passed_time":2.284404803,"remaining_time":0.97903063},
{"learn":[0.1060329124],"iteration":350,"passed_time":2.289947932,"remaining_time":0.9720861593},
{"learn":[0.1056689077],"iteration":351,"passed_time":2.29544297,"remaining_time":0.9651294308},
{"learn":[0.105361056],"iteration":352,"passed_time":2.300915086,"remaining_time":0.958171438},
{"learn":[0.1050795157],"iteration":353,"passed_time":2.306314173,"remaining_time":0.9511917211},
{"learn":[0.1048633376],"iteration":354,"passed_time":2.311729323,"remaining_time":0.9442274701},
{"learn":[0.1044529872],"iteration":355,"passed_time":2.317440731,"remaining_time":0.9373917562},
{"learn":[0.104084385],"iteration":356,"passed_time":2.322957267,"remaining_time":0.9304842833},
{"learn":[0.1038322093],"iteration":357,"passed_time":2.328471452,"remaining_time":0.9235836486},
{"learn":[0.1035342715],"iteration":358,"passed_time":2.333974604,"remaining_time":0.9166864043},
{"learn":[0.1032102072],"iteration":359,"passed_time":2.339500951,"remaining_time":0.9098059252},
{"learn":[0.1030397273],"iteration":360,"passed_time":2.3454584,"remaining_time":0.9030989408},
{"learn":[0.1027535681],"iteration":361,"passed_time":2.350999875,"remaining_time":0.8962375214},
{"learn":[0.1024240807],"iteration":362,"passed_time":2.356792221,"remaining_time":0.8894780559},
{"learn":[0.1020957178],"iteration":363,"passed_time":2.362433163,"remaining_time":0.8826673356},
{"learn":[0.101886365],"iteration":364,"passed_time":2.367950609,"remaining_time":0.8758173485},
{"learn":[0.101654067],"iteration":365,"passed_time":2.373540566,"remaining_time":0.869001191},
{"learn":[0.1013496954],"iteration":366,"passed_time":2.379373535,"remaining_time":0.8622797826},
{"learn":[0.101136962],"iteration":367,"passed_time":2.385162371,"remaining_time":0.8555473721},
{"learn":[0.1007868354],"iteration":368,"passed_time":2.39055241,"remaining_time":0.848678498},
{"learn":[0.1005299412],"iteration":369,"passed_time":2.396368225,"remaining_time":0.8419672142},
{"learn":[0.1002104674],"iteration":370,"passed_time":2.402135013,"remaining_time":0.8352437105},
{"learn":[0.09998838225],"iteration":371,"passed_time":2.407673798,"remaining_time":0.8284468981},
{"learn":[0.09962276914],"iteration":372,"passed_time":2.413155387,"remaining_time":0.8216373571},
{"learn":[0.09939360263],"iteration":373,"passed_time":2.41892721,"remaining_time":0.8149326963},
{"learn":[0.09918711079],"iteration":374,"passed_time":2.424421349,"remaining_time":0.8081404496},
{"learn":[0.09894200225],"iteration":375,"passed_time":2.429955138,"remaining_time":0.8013681839},
{"learn":[0.09857009774],"iteration":376,"passed_time":2.435609544,"remaining_time":0.7946418407},
{"learn":[0.09839989534],"iteration":377,"passed_time":2.441488391,"remaining_time":0.7879936077},
{"learn":[0.09815741297],"iteration":378,"passed_time":2.447396923,"remaining_time":0.7813589121},
{"learn":[0.09781616837],"iteration":379,"passed_time":2.453036751,"remaining_time":0.7746431845},
{"learn":[0.09757968561],"iteration":380,"passed_time":2.45844289,"remaining_time":0.7678601152},
{"learn":[0.09728792532],"iteration":381,"passed_time":2.464198466,"remaining_time":0.7611921962},
{"learn":[0.09698120516],"iteration":382,"passed_time":2.469987922,"remaining_time":0.7545393913},
{"learn":[0.09676671384],"iteration":383,"passed_time":2.475752955,"remaining_time":0.7478837053},
{"learn":[0.09644445732],"iteration":384,"passed_time":2.481563618,"remaining_time":0.7412462756},
{"learn":[0.09626003522],"iteration":385,"passed_time":2.487230511,"remaining_time":0.734570669},
{"learn":[0.09602848452],"iteration":386,"passed_time":2.493133976,"remaining_time":0.7279693523},
{"learn":[0.09570328157],"iteration":387,"passed_time":2.49888587,"remaining_time":0.7213278801},
{"learn":[0.09552142869],"iteration":388,"passed_time":2.504178862,"remaining_time":0.7145600352},
{"learn":[0.09532922062],"iteration":389,"passed_time":2.509604911,"remaining_time":0.7078372825},
{"learn":[0.09513458565],"iteration":390,"passed_time":2.515284983,"remaining_time":0.7011919773},
{"learn":[0.09485685292],"iteration":391,"passed_time":2.520703337,"remaining_time":0.6944794907},
{"learn":[0.09460295492],"iteration":392,"passed_time":2.526388724,"remaining_time":0.6878462939},
{"learn":[0.09433374832],"iteration":393,"passed_time":2.532207442,"remaining_time":0.6812537788},
{"learn":[0.09399747137],"iteration":394,"passed_time":2.537897249,"remaining_time":0.6746309144},
{"learn":[0.09370522001],"iteration":395,"passed_time":2.543275524,"remaining_time":0.6679309456},
{"learn":[0.09342318862],"iteration":396,"passed_time":2.548878861,"remaining_time":0.661296027},
{"learn":[0.09325893601],"iteration":397,"passed_time":2.554815506,"remaining_time":0.6547517126},
{"learn":[0.09305817334],"iteration":398,"passed_time":2.560379381,"remaining_time":0.6481160838},
{"learn":[0.09283048715],"iteration":399,"passed_time":2.563675028,"remaining_time":0.6409187571},
{"learn":[0.09256837617],"iteration":400,"passed_time":2.569273634,"remaining_time":0.6343094509},
{"learn":[0.09229657187],"iteration":401,"passed_time":2.574770977,"remaining_time":0.627680487},
{"learn":[0.09204386953],"iteration":402,"passed_time":2.580302578,"remaining_time":0.6210653847},
{"learn":[0.09172589743],"iteration":403,"passed_time":2.585752191,"remaining_time":0.6144361643},
{"learn":[0.09148048287],"iteration":404,"passed_time":2.591217108,"remaining_time":0.6078163587},
{"learn":[0.0912950288],"iteration":405,"passed_time":2.597125094,"remaining_time":0.6013048248},
{"learn":[0.09100681276],"iteration":406,"passed_time":2.603035976,"remaining_time":0.5947969184},
{"learn":[0.09066660013],"iteration":407,"passed_time":2.608385864,"remaining_time":0.5881654399},
{"learn":[0.09039184229],"iteration":408,"passed_time":2.613993097,"remaining_time":0.581597486},
{"learn":[0.0901023879],"iteration":409,"passed_time":2.619482904,"remaining_time":0.5750084424},
{"learn":[0.08985774908],"iteration":410,"passed_time":2.624914179,"remaining_time":0.5684120727},
{"learn":[0.08954441014],"iteration":411,"passed_time":2.630456219,"remaining_time":0.5618450177},
{"learn":[0.08925795199],"iteration":412,"passed_time":2.635953553,"remaining_time":0.5552735087},
{"learn":[0.08891043734],"iteration":413,"passed_time":2.641571309,"remaining_time":0.5487322042},
{"learn":[0.08865332959],"iteration":414,"passed_time":2.647217543,"remaining_time":0.5422011835},
{"learn":[0.08840733144],"iteration":415,"passed_time":2.653621135,"remaining_time":0.5358273446},
{"learn":[0.08824057366],"iteration":416,"passed_time":2.659104431,"remaining_time":0.5292701865},
{"learn":[0.08797585786],"iteration":417,"passed_time":2.665016204,"remaining_time":0.5228022218},
{"learn":[0.08779635358],"iteration":418,"passed_time":2.670467043,"remaining_time":0.5162478055},
{"learn":[0.08752897604],"iteration":419,"passed_time":2.676018654,"remaining_time":0.5097178388},
{"learn":[0.08733729462],"iteration":420,"passed_time":2.681359959,"remaining_time":0.5031530564},
{"learn":[0.08716519199],"iteration":421,"passed_time":2.687009304,"remaining_time":0.4966510088},
{"learn":[0.08696461436],"iteration":422,"passed_time":2.692704161,"remaining_time":0.4901612776},
{"learn":[0.08674062188],"iteration":423,"passed_time":2.698350917,"remaining_time":0.4836666737},
{"learn":[0.08647060394],"iteration":424,"passed_time":2.703840868,"remaining_time":0.4771483885},
{"learn":[0.08623101818],"iteration":425,"passed_time":2.709250909,"remaining_time":0.4706210499},
{"learn":[0.08602149451],"iteration":426,"passed_time":2.714693738,"remaining_time":0.46410455},
{"learn":[0.08573611815],"iteration":427,"passed_time":2.720290376,"remaining_time":0.4576189417},
{"learn":[0.0854878995],"iteration":428,"passed_time":2.725933083,"remaining_time":0.4511451024},
{"learn":[0.08526082537],"iteration":429,"passed_time":2.731424087,"remaining_time":0.4446504328},
{"learn":[0.08493101063],"iteration":430,"passed_time":2.737316384,"remaining_time":0.4382246647},
{"learn":[0.08469874823],"iteration":431,"passed_time":2.742688317,"remaining_time":0.4317194574},
{"learn":[0.08447736057],"iteration":432,"passed_time":2.748218702,"remaining_time":0.4252440024},
{"learn":[0.0842877573],"iteration":433,"passed_time":2.753686525,"remaining_time":0.4187633885},
{"learn":[0.08404074142],"iteration":434,"passed_time":2.759617617,"remaining_time":0.4123566553},
{"learn":[0.08373254804],"iteration":435,"passed_time":2.765282448,"remaining_time":0.4059130199},
{"learn":[0.08357469359],"iteration":436,"passed_time":2.770543022,"remaining_time":0.3994146691},
{"learn":[0.08323004708],"iteration":437,"passed_time":2.776958378,"remaining_time":0.3930854324},
{"learn":[0.08303546906],"iteration":438,"passed_time":2.782542567,"remaining_time":0.3866403112},
{"learn":[0.08281111361],"iteration":439,"passed_time":2.785469017,"remaining_time":0.3798366841},
{"learn":[0.08263074106],"iteration":440,"passed_time":2.790912391,"remaining_time":0.373387372},
{"learn":[0.08240286272],"iteration":441,"passed_time":2.796405819,"remaining_time":0.3669491799},
{"learn":[0.08215661547],"iteration":442,"passed_time":2.801934493,"remaining_time":0.360519788},
{"learn":[0.08187732412],"iteration":443,"passed_time":2.807371061,"remaining_time":0.3540828365},
{"learn":[0.08161862217],"iteration":444,"passed_time":2.813035608,"remaining_time":0.3476785583},
{"learn":[0.08145789246],"iteration":445,"passed_time":2.818267116,"remaining_time":0.3412251665},
{"learn":[0.08128902805],"iteration":446,"passed_time":2.82348376,"remaining_time":0.3347754793},
{"learn":[0.08106258022],"iteration":447,"passed_time":2.829102245,"remaining_time":0.3283779391},
{"learn":[0.08088996517],"iteration":448,"passed_time":2.83460326,"remaining_time":0.3219705262},
{"learn":[0.08071694445],"iteration":449,"passed_time":2.840115787,"remaining_time":0.3155684208},
{"learn":[0.0804706118],"iteration":450,"passed_time":2.845781897,"remaining_time":0.3091869467},
{"learn":[0.0803503919],"iteration":451,"passed_time":2.851240278,"remaining_time":0.3027865782},
{"learn":[0.08023269853],"iteration":452,"passed_time":2.856569337,"remaining_time":0.2963769511},
{"learn":[0.07999852878],"iteration":453,"passed_time":2.862450804,"remaining_time":0.290028055},
{"learn":[0.07975359817],"iteration":454,"passed_time":2.867899665,"remaining_time":0.2836384284},
{"learn":[0.07954031674],"iteration":455,"passed_time":2.873500634,"remaining_time":0.2772676051},
{"learn":[0.07940606929],"iteration":456,"passed_time":2.879050036,"remaining_time":0.2708952988},
{"learn":[0.07928330151],"iteration":457,"passed_time":2.884440416,"remaining_time":0.2645120032},
{"learn":[0.07909064506],"iteration":458,"passed_time":2.89021164,"remaining_time":0.2581670528},
{"learn":[0.07889753313],"iteration":459,"passed_time":2.895875676,"remaining_time":0.2518152762},
{"learn":[0.07874868877],"iteration":460,"passed_time":2.901289381,"remaining_time":0.2454453056},
{"learn":[0.07864000548],"iteration":461,"passed_time":2.906967484,"remaining_time":0.2391012217},
{"learn":[0.07848643545],"iteration":462,"passed_time":2.912432786,"remaining_time":0.2327430088},
{"learn":[0.07825660706],"iteration":463,"passed_time":2.918053077,"remaining_time":0.2264006698},
{"learn":[0.07805778019],"iteration":464,"passed_time":2.923286078,"remaining_time":0.2200322854},
{"learn":[0.07785372236],"iteration":465,"passed_time":2.928845442,"remaining_time":0.2136925859},
{"learn":[0.07766434684],"iteration":466,"passed_time":2.934752312,"remaining_time":0.2073807843},
{"learn":[0.07747437349],"iteration":467,"passed_time":2.940396769,"remaining_time":0.2010527706},
{"learn":[0.07722313013],"iteration":468,"passed_time":2.945829198,"remaining_time":0.194713657},
{"learn":[0.07701414735],"iteration":469,"passed_time":2.951091946,"remaining_time":0.188367571},
{"learn":[0.07683180339],"iteration":470,"passed_time":2.956715315,"remaining_time":0.182048289},
{"learn":[0.07668123672],"iteration":471,"passed_time":2.962521238,"remaining_time":0.1757427853},
{"learn":[0.0765004158],"iteration":472,"passed_time":2.968260178,"remaining_time":0.1694355704},
{"learn":[0.07626017528],"iteration":473,"passed_time":2.974019352,"remaining_time":0.1631318632},
{"learn":[0.0761067974],"iteration":474,"passed_time":2.979619383,"remaining_time":0.1568220728},
{"learn":[0.07588898958],"iteration":475,"passed_time":2.985402698,"remaining_time":0.1505245058},
{"learn":[0.07562728426],"iteration":476,"passed_time":2.990867234,"remaining_time":0.1442137241},
{"learn":[0.075458185],"iteration":477,"passed_time":2.996590272,"remaining_time":0.1379183807},
{"learn":[0.07526011965],"iteration":478,"passed_time":3.002109476,"remaining_time":0.1316164906},
{"learn":[0.07506776212],"iteration":479,"passed_time":3.007576887,"remaining_time":0.1253157036},
{"learn":[0.0749316856],"iteration":480,"passed_time":3.013356218,"remaining_time":0.119030703},
{"learn":[0.07478901877],"iteration":481,"passed_time":3.018681922,"remaining_time":0.1127308601},
{"learn":[0.07462986903],"iteration":482,"passed_time":3.024014247,"remaining_time":0.1064352841},
{"learn":[0.07439418337],"iteration":483,"passed_time":3.029438068,"remaining_time":0.100146713},
{"learn":[0.07426009961],"iteration":484,"passed_time":3.03489144,"remaining_time":0.09386262184},
{"learn":[0.07408287988],"iteration":485,"passed_time":3.040328678,"remaining_time":0.08758148455},
{"learn":[0.07383414881],"iteration":486,"passed_time":3.04595888,"remaining_time":0.08130896395},
{"learn":[0.07366037369],"iteration":487,"passed_time":3.051699475,"remaining_time":0.07504179037},
{"learn":[0.07352101625],"iteration":488,"passed_time":3.057651036,"remaining_time":0.06878151614},
{"learn":[0.07335694868],"iteration":489,"passed_time":3.064733161,"remaining_time":0.06254557471},
{"learn":[0.07321104363],"iteration":490,"passed_time":3.070748357,"remaining_time":0.05628662976},
{"learn":[0.07299491541],"iteration":491,"passed_time":3.076307092,"remaining_time":0.05002125352},
{"learn":[0.07279734825],"iteration":492,"passed_time":3.082151896,"remaining_time":0.04376280583},
{"learn":[0.0726822241],"iteration":493,"passed_time":3.087555646,"remaining_time":0.03750067586},
{"learn":[0.07251601433],"iteration":494,"passed_time":3.093385628,"remaining_time":0.03124631948},
{"learn":[0.07233472369],"iteration":495,"passed_time":3.099578724,"remaining_time":0.02499660261},
{"learn":[0.07212210413],"iteration":496,"passed_time":3.105397097,"remaining_time":0.01874485169},
{"learn":[0.07194861369],"iteration":497,"passed_time":3.111106809,"remaining_time":0.01249440485},
{"learn":[0.07180704288],"iteration":498,"passed_time":3.117119423,"remaining_time":0.00624673231},
{"learn":[0.07159338424],"iteration":499,"passed_time":3.122828469,"remaining_time":0}
]}